fizzgun/__init__.py
fizzgun/fizzgun_exception.py
fizzgun/util.py
fizzgun/application/__init__.py
fizzgun/application/dependencies.py
fizzgun/application/service_contexts.py
fizzgun/bin/__init__.py
fizzgun/bin/cli.py
fizzgun/bin/cli_commands.py
fizzgun/bubbles/__init__.py
fizzgun/bubbles/bubble.py
fizzgun/bubbles/bubble_arsenal.py
fizzgun/bubbles/builtin_bubbles.py
fizzgun/bubbles/data_validation/__init__.py
fizzgun/bubbles/data_validation/enlarger.py
fizzgun/bubbles/data_validation/trimmer.py
fizzgun/bubbles/data_validation/type_changer.py
fizzgun/bubbles/security/__init__.py
fizzgun/bubbles/security/injector.py
fizzgun/bubbles/security/shellshock.py
fizzgun/bubbles/utils/__init__.py
fizzgun/bubbles/utils/bubble_delegate.py
fizzgun/bubbles/utils/composite_delegate.py
fizzgun/bubbles/utils/json_delegate.py
fizzgun/bubbles/utils/urlencoded_delegate.py
fizzgun/config/__init__.py
fizzgun/config/config.py
fizzgun/config/defaults.py
fizzgun/core/__init__.py
fizzgun/core/assertor.py
fizzgun/core/common.py
fizzgun/core/deployment.py
fizzgun/core/dispatcher.py
fizzgun/core/filter.py
fizzgun/core/producer.py
fizzgun/core/reporter.py
fizzgun/core/requestor.py
fizzgun/core/transformer.py
fizzgun/data/config_defaults.yaml
fizzgun/data/config_template.yaml
fizzgun/data/templates/directory.html
fizzgun/data/templates/frame.html
fizzgun/data/templates/index.html
fizzgun/data/templates/layout.html
fizzgun/data/templates/mustache/html_report_entry.mustache
fizzgun/data/templates/mustache/txt_report_entry.mustache
fizzgun/impl/__init__.py
fizzgun/impl/fizzgun_runner.py
fizzgun/impl/queue_flow.py
fizzgun/impl/zmq_flow.py
fizzgun/impl/mitm_plugin/__init__.py
fizzgun/impl/mitm_plugin/bootstrap.py
fizzgun/impl/mitm_plugin/mitm_plugin.py
fizzgun/impl/mitm_plugin/onboarding_extensions.py
fizzgun/models/__init__.py
fizzgun/models/expectation.py
fizzgun/models/http_request.py
fizzgun/models/http_request_builder.py
fizzgun-0.4.0.dist-info/DESCRIPTION.rst
fizzgun-0.4.0.dist-info/LICENSE.txt
fizzgun-0.4.0.dist-info/METADATA
fizzgun-0.4.0.dist-info/RECORD
fizzgun-0.4.0.dist-info/WHEEL
fizzgun-0.4.0.dist-info/entry_points.txt
fizzgun-0.4.0.dist-info/metadata.json
fizzgun-0.4.0.dist-info/top_level.txt
